markdownsausagemachine-0.2.3.dist-info/METADATA
markdownsausagemachine-0.2.3.dist-info/WHEEL
markdownsausagemachine-0.2.3.dist-info/entry_points.txt
markdownsausagemachine-0.2.3.dist-info/licenses/LICENSE
markdownsausagemachine/__init__.py
markdownsausagemachine/contents.py
markdownsausagemachine/contents_codeblock.py
markdownsausagemachine/contents_list.py
markdownsausagemachine/contents_paragraph.py
markdownsausagemachine/document.py
markdownsausagemachine/examples/contents_codeblocks.py
markdownsausagemachine/examples/contents_lists.py
markdownsausagemachine/examples/contents_paragraphs.py
markdownsausagemachine/examples/document_links.py
markdownsausagemachine/examples/documents.py
markdownsausagemachine/examples/sausage_man.py
markdownsausagemachine/examples/unmet_promise.py
markdownsausagemachine/py.typed
markdownsausagemachine/sausage_machine.py
markdownsausagemachine/sausage_man.py
markdownsausagemachine/version.py
markdownsausagemachine-0.2.3.dist-info/RECORD
