Metadata-Version: 2.1
Name: markdownsausagemachine
Version: 0.2.3
Summary: A library to creates markdown documents programatically
Author-Email: Michael Ho <michael.ho@ieee.org>
License: MIT
Requires-Python: >=3.11
